svdep/__init__.py
svdep/__main__.py
svdep/__version__.py
svdep/file_collection.py
svdep/file_deps_report.py
svdep/file_info.py
svdep/hash_files.py
svdep/native.py
svdep/svpp_lexer.py
svdep/task_build_file_collection.py
svdep/task_check_up_to_date.py
svdep-0.0.1.21536803277.dist-info/LICENSE
svdep-0.0.1.21536803277.dist-info/METADATA
svdep-0.0.1.21536803277.dist-info/WHEEL
svdep-0.0.1.21536803277.dist-info/top_level.txt
svdep-0.0.1.21536803277.dist-info/RECORD
