Metadata-Version: 2.1
Name: svdep
Version: 0.0.1.21536803277
Summary: Checks whether SystemVerilog need to be recompiled
Author-email: Matthew Ballance <matt.ballance@gmail.com>
License: Apache-2.0
License-File: LICENSE
Requires-Dist: ply
